setup.py
src/margin/__init__.py
src/margin/marginAlignLib.py
src/margin/marginCallerLib.py
src/margin/utils.py
src/margin/toil/__init__.py
src/margin/toil/alignment.py
src/margin/toil/bwa.py
src/margin/toil/chainAlignment.py
src/margin/toil/expectationMaximisation.py
src/margin/toil/hmm.py
src/margin/toil/localFileManager.py
src/margin/toil/realign.py
src/margin/toil/shardAlignment.py
src/margin/toil/stats.py
src/margin/toil/variantCall.py
src/margin/toil/variantCaller.py
src/marginAlign.egg-info/PKG-INFO
src/marginAlign.egg-info/SOURCES.txt
src/marginAlign.egg-info/dependency_links.txt
src/marginAlign.egg-info/requires.txt
src/marginAlign.egg-info/top_level.txt