Metadata-Version: 1.0
Name: marginAlign
Version: 1.1.8
Summary: Toil-based functions for performing MinION sequence analysis
Home-page: https://github.com/ArtRand/marginAlign
Author: Benedict Paten and Art Rand
Author-email: benedict@soe.ucsc.edu, arand@soe.ucsc.edu
License: UNKNOWN
Platform: UNKNOWN
